affinidi_tdk_wallets_client/__init__.py
affinidi_tdk_wallets_client/api/__init__.py
affinidi_tdk_wallets_client/api/revocation_api.py
affinidi_tdk_wallets_client/api/wallet_api.py
affinidi_tdk_wallets_client/api_client.py
affinidi_tdk_wallets_client/api_response.py
affinidi_tdk_wallets_client/configuration.py
affinidi_tdk_wallets_client/exceptions.py
affinidi_tdk_wallets_client/models/__init__.py
affinidi_tdk_wallets_client/models/authcrypt_message_input.py
affinidi_tdk_wallets_client/models/authcrypt_message_result_dto.py
affinidi_tdk_wallets_client/models/create_wallet_input.py
affinidi_tdk_wallets_client/models/create_wallet_response.py
affinidi_tdk_wallets_client/models/create_wallet_v2_input.py
affinidi_tdk_wallets_client/models/create_wallet_v2_response.py
affinidi_tdk_wallets_client/models/entity_not_found_error.py
affinidi_tdk_wallets_client/models/get_revocation_credential_status_ok.py
affinidi_tdk_wallets_client/models/get_revocation_list_credential_result_dto.py
affinidi_tdk_wallets_client/models/invalid_did_parameter_error.py
affinidi_tdk_wallets_client/models/invalid_parameter_error.py
affinidi_tdk_wallets_client/models/key_not_found_error.py
affinidi_tdk_wallets_client/models/not_found_error.py
affinidi_tdk_wallets_client/models/operation_forbidden_error.py
affinidi_tdk_wallets_client/models/revoke_credential_input.py
affinidi_tdk_wallets_client/models/revoke_credentials_input.py
affinidi_tdk_wallets_client/models/service_error_response.py
affinidi_tdk_wallets_client/models/service_error_response_details_inner.py
affinidi_tdk_wallets_client/models/sign_credential400_response.py
affinidi_tdk_wallets_client/models/sign_credential_input_dto.py
affinidi_tdk_wallets_client/models/sign_credential_input_dto_unsigned_credential_params.py
affinidi_tdk_wallets_client/models/sign_credential_result_dto.py
affinidi_tdk_wallets_client/models/sign_credentials_dm1_ld_input_dto.py
affinidi_tdk_wallets_client/models/sign_credentials_dm1_ld_result_dto.py
affinidi_tdk_wallets_client-1.61.0.dist-info/METADATA
affinidi_tdk_wallets_client-1.61.0.dist-info/WHEEL
affinidi_tdk_wallets_client-1.61.0.dist-info/RECORD
